dapter/__init__.py
dapter/column_names.py
dapter/core.py
dapter/utils.py
dapter-0.1.1.dist-info/METADATA
dapter-0.1.1.dist-info/WHEEL
dapter-0.1.1.dist-info/RECORD
