Metadata-Version: 2.3
Name: dapter
Version: 0.1.1
Summary: Tool to adapt multiple dataframes to one unique format
Author-email: Luciano Scarpulla <66913960+lucianosrp@users.noreply.github.com>
Requires-Python: >=3.8
Requires-Dist: narwhals>=1.2.0
